helpers.py
rangify.py
rangify-0.0.8.dist-info/LICENSE.txt
rangify-0.0.8.dist-info/METADATA
rangify-0.0.8.dist-info/WHEEL
rangify-0.0.8.dist-info/top_level.txt
rangify-0.0.8.dist-info/RECORD
