Metadata-Version: 2.1
Name: rangify
Version: 0.0.8
Summary: cisco interface rangifier
Home-page: UNKNOWN
Author: Nijat Aliyev
Author-email: nicataliyev@gmail.com
License: UNKNOWN
Platform: UNKNOWN
Classifier: Intended Audience :: Education
Classifier: Operating System :: OS Independent
Classifier: License :: OSI Approved :: MIT License
Classifier: Programming Language :: Python :: 3.9
Classifier: Programming Language :: Python :: 3.8
Classifier: Programming Language :: Python :: 3
Requires-Dist: deepdiff (==5.5.0)
